DistUtilsExtra/__init__.py
DistUtilsExtra/auto.py
DistUtilsExtra/command/__init__.py
DistUtilsExtra/command/build_extra.py
DistUtilsExtra/command/build_help.py
DistUtilsExtra/command/build_i18n.py
DistUtilsExtra/command/build_icons.py
DistUtilsExtra/command/clean_i18n.py
DistUtilsExtra/command/pylint.py
distutils_extra_python-2.39.2.dist-info/LICENSE
distutils_extra_python-2.39.2.dist-info/METADATA
distutils_extra_python-2.39.2.dist-info/WHEEL
distutils_extra_python-2.39.2.dist-info/entry_points.txt
distutils_extra_python-2.39.2.dist-info/top_level.txt
distutils_extra_python-2.39.2.dist-info/RECORD
